vaughntech_cdk_nodejs_powertools_lambda_layer/__init__.py
vaughntech_cdk_nodejs_powertools_lambda_layer/py.typed
vaughntech_cdk_nodejs_powertools_lambda_layer/_jsii/__init__.py
vaughntech_cdk_nodejs_powertools_lambda_layer/_jsii/vaughntech-nodejs-powertools-lambdalayer@0.0.11.jsii.tgz
vaughntech.cdk_nodejs_powertools_lambda_layer-0.0.11.dist-info/LICENSE
vaughntech.cdk_nodejs_powertools_lambda_layer-0.0.11.dist-info/METADATA
vaughntech.cdk_nodejs_powertools_lambda_layer-0.0.11.dist-info/WHEEL
vaughntech.cdk_nodejs_powertools_lambda_layer-0.0.11.dist-info/top_level.txt
vaughntech.cdk_nodejs_powertools_lambda_layer-0.0.11.dist-info/RECORD
