Metadata-Version: 2.1
Name: vaughntech.cdk-nodejs-powertools-lambda-layer
Version: 0.0.11
Summary: A suite of utilities for AWS Lambda functions running on the Node.js runtime, to ease adopting best practices such as tracing, structured logging, custom metrics.
Home-page: https://github.com/vaughngit/projen-nodejs-powertools-lambda-layer-cdk-construct.git
Author: VaughnGit<alvin.vaughn@outlook.com>
License: Apache-2.0
Project-URL: Source, https://github.com/vaughngit/projen-nodejs-powertools-lambda-layer-cdk-construct.git
Platform: UNKNOWN
Classifier: Intended Audience :: Developers
Classifier: Operating System :: OS Independent
Classifier: Programming Language :: JavaScript
Classifier: Programming Language :: Python :: 3 :: Only
Classifier: Programming Language :: Python :: 3.7
Classifier: Programming Language :: Python :: 3.8
Classifier: Programming Language :: Python :: 3.9
Classifier: Programming Language :: Python :: 3.10
Classifier: Typing :: Typed
Classifier: Development Status :: 5 - Production/Stable
Classifier: License :: OSI Approved
Requires-Python: ~=3.7
License-File: LICENSE
Requires-Dist: aws-cdk-lib (<3.0.0,>=2.57.0)
Requires-Dist: constructs (<11.0.0,>=10.0.5)
Requires-Dist: jsii (<2.0.0,>=1.72.0)
Requires-Dist: publication (>=0.0.3)
Requires-Dist: typeguard (~=2.13.3)
